napari_pssr/__init__.py
napari_pssr/_version.py
napari_pssr/napari.yaml
napari_pssr/sample_data.py
napari_pssr/_tests/__init__.py
napari_pssr/_tests/test_widget.py
napari_pssr/bioimageio/__init__.py
napari_pssr/bioimageio/helpers.py
napari_pssr/gp/__init__.py
napari_pssr/gp/pipeline.py
napari_pssr/gp/nodes/__init__.py
napari_pssr/gp/nodes/binarize.py
napari_pssr/gp/nodes/napari_image_source.py
napari_pssr/gp/nodes/napari_label_source.py
napari_pssr/gp/nodes/np_source.py
napari_pssr/gp/nodes/ones_source.py
napari_pssr/sample_data/LR/8nm_em_sample/00.tif
napari_pssr/sample_data/LR/8nm_em_sample/01.tif
napari_pssr/sample_data/LR/8nm_em_sample/02.tif
napari_pssr/sample_data/LR/8nm_em_sample/03.tif
napari_pssr/sample_data/LR/8nm_em_sample/04.tif
napari_pssr/sample_data/LR/8nm_em_sample/05.tif
napari_pssr/widgets/__init__.py
napari_pssr/widgets/gui_helpers.py
napari_pssr/widgets/pssr.py
napari_pssr-0.1.dist-info/LICENSE
napari_pssr-0.1.dist-info/METADATA
napari_pssr-0.1.dist-info/WHEEL
napari_pssr-0.1.dist-info/entry_points.txt
napari_pssr-0.1.dist-info/top_level.txt
napari_pssr-0.1.dist-info/RECORD
