Metadata-Version: 2.1
Name: napari-pssr
Version: 0.1
Summary: A plugin for training and applying pssr
Home-page: https://github.com/pattonw/napari-pssr
Author: William Patton
Author-email: will.hunter.patton@gmail.com
License: MIT
Project-URL: Bug Tracker, https://github.com/pattonw/napari-pssr/issues
Project-URL: Documentation, https://github.com/pattonw/napari-pssr#README.md
Project-URL: Source Code, https://github.com/pattonw/napari-pssr
Project-URL: User Support, https://github.com/pattonw/napari-pssr/issues
Classifier: Development Status :: 2 - Pre-Alpha
Classifier: Intended Audience :: Developers
Classifier: Framework :: napari
Classifier: Topic :: Software Development :: Testing
Classifier: Programming Language :: Python
Classifier: Programming Language :: Python :: 3
Classifier: Programming Language :: Python :: 3.7
Classifier: Programming Language :: Python :: 3.8
Classifier: Programming Language :: Python :: 3.9
Classifier: Operating System :: OS Independent
Classifier: License :: OSI Approved :: MIT License
Requires-Python: >=3.7
License-File: LICENSE
Requires-Dist: numpy
Requires-Dist: zarr
Requires-Dist: magicgui
Requires-Dist: bioimageio.core
Requires-Dist: gunpowder
Requires-Dist: matplotlib
Requires-Dist: torch
Requires-Dist: napari
